{
  "name": "admin",
  "description": "Full administrative access to all resources",
  "kv": [
    {
      "path": "*",
      "capabilities": ["read", "write", "list", "delete"]
    }
  ],
  "service": [
    {
      "name": "*",
      "capabilities": ["read", "write", "list", "register", "deregister"]
    }
  ],
  "health": [
    {
      "capabilities": ["read", "write"]
    }
  ],
  "backup": [
    {
      "capabilities": ["create", "restore", "export", "import"]
    }
  ],
  "admin": [
    {
      "capabilities": ["read", "write", "admin"]
    }
  ]
}
